iflow_mcp_abhiemj_manim_mcp_server-1.0.0.dist-info/licenses/LICENSE.txt
manim_server/__init__.py
iflow_mcp_abhiemj_manim_mcp_server-1.0.0.dist-info/METADATA
iflow_mcp_abhiemj_manim_mcp_server-1.0.0.dist-info/WHEEL
iflow_mcp_abhiemj_manim_mcp_server-1.0.0.dist-info/entry_points.txt
iflow_mcp_abhiemj_manim_mcp_server-1.0.0.dist-info/top_level.txt
iflow_mcp_abhiemj_manim_mcp_server-1.0.0.dist-info/RECORD
