Metadata-Version: 2.4
Name: iflow-mcp-abhiemj-manim-mcp-server
Version: 1.0.0
Summary: MCP server for executing Manim animation code and generating videos
Author: abhiemj
License: MIT
Project-URL: Homepage, https://github.com/abhiemj/manim-mcp-server
Project-URL: Repository, https://github.com/abhiemj/manim-mcp-server
Project-URL: Issues, https://github.com/abhiemj/manim-mcp-server/issues
Keywords: mcp,manim,animation,video,model-context-protocol
Classifier: Development Status :: 4 - Beta
Classifier: Intended Audience :: Developers
Classifier: License :: OSI Approved :: MIT License
Classifier: Programming Language :: Python :: 3
Classifier: Programming Language :: Python :: 3.8
Classifier: Programming Language :: Python :: 3.9
Classifier: Programming Language :: Python :: 3.10
Classifier: Programming Language :: Python :: 3.11
Classifier: Programming Language :: Python :: 3.12
Requires-Python: >=3.8
License-File: LICENSE.txt
Requires-Dist: mcp>=1.0.0
Provides-Extra: manim
Requires-Dist: manim; extra == "manim"
Dynamic: license-file
